Workbook

Sheet Dashboard
A2: CONFIGURACIÓN
J3: Tipo | K3: Porcentagem
A4: Investimento Inicial | B4: 10000 | E4: PATRIMÔNIO TOTAL | F4: =FV(B7, B6*12, -B5, -B4) -> 126126.13 | J4: PAPEL | K4: =SUMIFS('Configurações e Perfis'!D:D, 'Configurações e Perfis'!B:B, B9, 'Configurações e Perfis'!C:C, "PAPEL") -> 0.5
A5: Aporte Mensal | B5: 500 | J5: TIJOLO | K5: =SUMIFS('Configurações e Perfis'!D:D, 'Configurações e Perfis'!B:B, B9, 'Configurações e Perfis'!C:C, "TIJOLO") -> 0.3
A6: Anos | B6: 10 | E6: RENDA MENSAL | F6: =F4 * B7 -> 1009.0091 | J6: HÍBRIDOS | K6: =SUMIFS('Configurações e Perfis'!D:D, 'Configurações e Perfis'!B:B, B9, 'Configurações e Perfis'!C:C, "HÍBRIDOS") -> 0.1
A7: Taxa Mensal (%) | B7: 0.008 | J7: FOFs | K7: =SUMIFS('Configurações e Perfis'!D:D, 'Configurações e Perfis'!B:B, B9, 'Configurações e Perfis'!C:C, "FOFs") -> 0.1
E8: DINHEIRO DO BOLSO | F8: =B4 + (B5 * B6 * 12) -> 70000 | J8: DESENVOLVIMENTO | K8: =SUMIFS('Configurações e Perfis'!D:D, 'Configurações e Perfis'!B:B, B9, 'Configurações e Perfis'!C:C, "DESENVOLVIMENTO") -> 0
A9: Perfil de Investimento | B9: Conservador | J9: HOTELARIA | K9: =SUMIFS('Configurações e Perfis'!D:D, 'Configurações e Perfis'!B:B, B9, 'Configurações e Perfis'!C:C, "HOTELARIA") -> 0
A19: STATUS | B19: =IF(E6 > B5, "Meta Batida! 🎉", "Continue focado!") -> Meta Batida! 🎉

Sheet Evolução Mensal
A1: Mês | B1: Saldo Inicial | C1: Aporte Mensal | D1: Dividendos (Juros) | E1: Saldo Final
A2: 1 | B2: =Dashboard!B4 -> 10000 | C2: =Dashboard!B5 -> 500 | D2: =B2 * Dashboard!B7 -> 80 | E2: =B2 + C2 + D2 -> 10580
A3: =A2+1 -> 2 | B3: =E2 -> 10580 | C3: =C2 -> 500 | D3: =B3 * Dashboard!$B$7 -> 84.64 | E3: =B3 + C3 + D3 -> 11164.64
A4: =A3+1 -> 3 | B4: =E3 -> 11164.64 | C4: =C3 -> 500 | D4: =B4 * Dashboard!$B$7 -> 89.31712 | E4: =B4 + C4 + D4 -> 11753.957
A5: =A4+1 -> 4 | B5: =E4 -> 11753.957 | C5: =C4 -> 500 | D5: =B5 * Dashboard!$B$7 -> 94.031657 | E5: =B5 + C5 + D5 -> 12347.989
A6: =A5+1 -> 5 | B6: =E5 -> 12347.989 | C6: =C5 -> 500 | D6: =B6 * Dashboard!$B$7 -> 98.78391 | E6: =B6 + C6 + D6 -> 12946.773
A7: =A6+1 -> 6 | B7: =E6 -> 12946.773 | C7: =C6 -> 500 | D7: =B7 * Dashboard!$B$7 -> 103.57418 | E7: =B7 + C7 + D7 -> 13550.347
A8: =A7+1 -> 7 | B8: =E7 -> 13550.347 | C8: =C7 -> 500 | D8: =B8 * Dashboard!$B$7 -> 108.40277 | E8: =B8 + C8 + D8 -> 14158.75
A9: =A8+1 -> 8 | B9: =E8 -> 14158.75 | C9: =C8 -> 500 | D9: =B9 * Dashboard!$B$7 -> 113.27 | E9: =B9 + C9 + D9 -> 14772.02
A10: =A9+1 -> 9 | B10: =E9 -> 14772.02 | C10: =C9 -> 500 | D10: =B10 * Dashboard!$B$7 -> 118.17616 | E10: =B10 + C10 + D10 -> 15390.196
A11: =A10+1 -> 10 | B11: =E10 -> 15390.196 | C11: =C10 -> 500 | D11: =B11 * Dashboard!$B$7 -> 123.12157 | E11: =B11 + C11 + D11 -> 16013.317
A12: =A11+1 -> 11 | B12: =E11 -> 16013.317 | C12: =C11 -> 500 | D12: =B12 * Dashboard!$B$7 -> 128.10654 | E12: =B12 + C12 + D12 -> 16641.424
A13: =A12+1 -> 12 | B13: =E12 -> 16641.424 | C13: =C12 -> 500 | D13: =B13 * Dashboard!$B$7 -> 133.13139 | E13: =B13 + C13 + D13 -> 17274.555
A14: =A13+1 -> 13 | B14: =E13 -> 17274.555 | C14: =C13 -> 500 | D14: =B14 * Dashboard!$B$7 -> 138.19644 | E14: =B14 + C14 + D14 -> 17912.752
... A31: =A30+1 -> 30 | B31: =E30 -> 28846.821 | C31: =C30 -> 500 | D31: =B31 * Dashboard!$B$7 -> 230.77457 | E31: =B31 + C31 + D31 -> 29577.596

Sheet Configurações e Perfis
B2: Perfil | C2: Tipo de FII | D2: % Alocação
B3: Conservador | C3: TIJOLO | D3: 0.3
B4: Conservador | C4: PAPEL | D4: 0.5
B5: Conservador | C5: HÍBRIDOS | D5: 0.1
B6: Conservador | C6: FOFs | D6: 0.1
B7: Conservador | C7: DESENVOLVIMENTO | D7: 0
B8: Conservador | C8: HOTELARIA | D8: 0
B9: Moderado | C9: TIJOLO | D9: 0.32
B10: Moderado | C10: PAPEL | D10: 0.35
B11: Moderado | C11: HÍBRIDOS | D11: 0.08
B12: Moderado | C12: FOFs | D12: 0.05
B13: Moderado | C13: DESENVOLVIMENTO | D13: 0.1
B14: Moderado | C14: HOTELARIA | D14: 0.1
... B20: Agressivo | C20: HOTELARIA | D20: 0.1

Sheet Ativos
A1: TIPO | B1: TICKET (Código) | C1: NOME DO FUNDO | D1: DESCRIÇÃO
A2: PAPEL | B2: MXRF11 | C2: Maxi Renda | D2: O mais popular, investe em dívida imobiliária.
A3: PAPEL | B3: CPTS11 | C3: Capitânia Securities | D3: Foco em títulos de crédito (CRIs).
A4: TIJOLO | B4: HGLG11 | C4: CSHG Logística | D4: Galpões logísticos de alto padrão.
A5: TIJOLO | B5: XPML11 | C5: XP Malls | D5: Shoppings em grandes cidades.
A6: HÍBRIDO | B6: KNRI11 | C6: Kinea Renda | D6: Mistura escritórios e galpões.
E11: Sugestão de Ativos para Você | G11: {=_xlfn._xlws.FILTER(Ativos!B:C, Ativos!A:A="PAPEL")} -> MXRF11 | H11: Maxi Renda
G12: CPTS11 | H12: Capitânia Securities
